goodmock.py
goodmock-0.0.1.dist-info/LICENSE
goodmock-0.0.1.dist-info/METADATA
goodmock-0.0.1.dist-info/WHEEL
goodmock-0.0.1.dist-info/top_level.txt
goodmock-0.0.1.dist-info/RECORD
