Metadata-Version: 2.1
Name: goodmock
Version: 0.0.1
Summary: A good mock library for python
Author-email: Schuyler Goodman <schuyler.goodman@gmail.com>
License: 
Project-URL: Homepage, https://github.com/SchuylerGoodman/goodmock
Project-URL: Bug Tracker, https://github.com/SchuylerGoodman/goodmock/issues
Classifier: Programming Language :: Python :: 3.10
Classifier: License :: OSI Approved :: Apache Software License
Requires-Python: >=3.10
License-File: LICENSE
